MANIFEST.in
README.rst
setup.py
anti/__init__.py
anti/anti.py
anti/anti_config.py
anti/context.py
anti/decorators.py
anti/metrika.py
anti/mixin.py
anti/seoutils.py
anti/tests.py
anti/utils.py
anti/webmaster.py
anti.egg-info/PKG-INFO
anti.egg-info/SOURCES.txt
anti.egg-info/dependency_links.txt
anti.egg-info/not-zip-safe
anti.egg-info/requires.txt
anti.egg-info/top_level.txt