Metadata-Version: 1.1
Name: anti
Version: 3.2.8
Summary: SeoUtils
Home-page: https://gprohorenko@bitbucket.org/gprohorenko/anti
Author: blinchik
Author-email: prohorenko_gena_@mail.ru
License: MIT License
Download-URL: https://bitbucket.org/gprohorenko/anti/downloads/anti.tar.gz
Platform: UNKNOWN
